{
  "nextCursor": 1,
  "transactions": [
    {
      "date": "2021-03-15",
      "transactions": [
        {
          "amount": 150,
          "awardPeriodId": 2,
          "cashback": 15,
          "circuitType": "01",
          "hashPan": "hPan",
          "idTrx": "trx01",
          "idTrxAcquirer": "idTrxAcquirer",
          "idTrxIssuer": "idTrxIssuer",
          "trxDate": "2021-03-15T10:15:51.726Z"
        }
      ]
    },
    {
      "date": "2021-02-12",
      "transactions": [
        {
          "amount": 150,
          "awardPeriodId": 2,
          "cashback": 15,
          "circuitType": "01",
          "hashPan": "hPan",
          "idTrx": "trx02",
          "idTrxAcquirer": "idTrxAcquirer",
          "idTrxIssuer": "idTrxIssuer",
          "trxDate": "2021-02-12T23:15:51.726Z"
        },
        {
          "amount": 150,
          "awardPeriodId": 2,
          "cashback": 15,
          "circuitType": "01",
          "hashPan": "hPan",
          "idTrx": "trx03",
          "idTrxAcquirer": "idTrxAcquirer",
          "idTrxIssuer": "idTrxIssuer",
          "trxDate": "2021-02-12T22:15:51.726Z"
        },
        {
          "amount": 150,
          "awardPeriodId": 2,
          "cashback": 15,
          "circuitType": "01",
          "hashPan": "hPan",
          "idTrx": "trx04",
          "idTrxAcquirer": "idTrxAcquirer",
          "idTrxIssuer": "idTrxIssuer",
          "trxDate": "2021-02-12T21:15:51.726Z"
        },
        {
          "amount": 150,
          "awardPeriodId": 2,
          "cashback": 15,
          "circuitType": "01",
          "hashPan": "hPan",
          "idTrx": "trx05",
          "idTrxAcquirer": "idTrxAcquirer",
          "idTrxIssuer": "idTrxIssuer",
          "trxDate": "2021-02-12T20:15:51.726Z"
        },
        {
          "amount": 150,
          "awardPeriodId": 2,
          "cashback": 15,
          "circuitType": "01",
          "hashPan": "hPan",
          "idTrx": "trx06",
          "idTrxAcquirer": "idTrxAcquirer",
          "idTrxIssuer": "idTrxIssuer",
          "trxDate": "2021-02-12T19:15:51.726Z"
        },
        {
          "amount": 150,
          "awardPeriodId": 2,
          "cashback": 15,
          "circuitType": "01",
          "hashPan": "hPan",
          "idTrx": "trx07",
          "idTrxAcquirer": "idTrxAcquirer",
          "idTrxIssuer": "idTrxIssuer",
          "trxDate": "2021-02-12T18:15:51.726Z"
        },
        {
          "amount": 150,
          "awardPeriodId": 2,
          "cashback": 15,
          "circuitType": "01",
          "hashPan": "hPan",
          "idTrx": "trx08",
          "idTrxAcquirer": "idTrxAcquirer",
          "idTrxIssuer": "idTrxIssuer",
          "trxDate": "2021-02-12T17:15:51.726Z"
        },
        {
          "amount": 150,
          "awardPeriodId": 2,
          "cashback": 15,
          "circuitType": "01",
          "hashPan": "hPan",
          "idTrx": "trx09",
          "idTrxAcquirer": "idTrxAcquirer",
          "idTrxIssuer": "idTrxIssuer",
          "trxDate": "2021-02-12T10:15:51.726Z"
        },
        {
          "amount": 150,
          "awardPeriodId": 2,
          "cashback": 15,
          "circuitType": "01",
          "hashPan": "hPan",
          "idTrx": "trx10",
          "idTrxAcquirer": "idTrxAcquirer",
          "idTrxIssuer": "idTrxIssuer",
          "trxDate": "2021-02-12T10:15:51.726Z"
        }
      ]
    }
  ]
}